pandasfruit/__init__.py
pandasfruit/pandasfruit.py
pandasfruit-1.4.1.dist-info/LICENSE
pandasfruit-1.4.1.dist-info/METADATA
pandasfruit-1.4.1.dist-info/WHEEL
pandasfruit-1.4.1.dist-info/top_level.txt
pandasfruit-1.4.1.dist-info/RECORD
