Metadata-Version: 2.1
Name: pandasfruit
Version: 1.4.1
Summary: Takes a pandas dataframe and returns more-narrow narrow markdown string suitable for printing in a Jupyter notebook.
Author-email: bol001 <info@bollingensoftware.com>
Project-URL: Homepage, https://github.com/bol001/pandasfruit
Project-URL: Issues, https://github.com/bol001/pandasfruit/issues
Keywords: pandas,jupyter,fit,dataframe,pdf
Classifier: Programming Language :: Python :: 3
Classifier: License :: OSI Approved :: MIT License
Classifier: Operating System :: OS Independent
Requires-Python: >=3.8
License-File: LICENSE
Requires-Dist: pandas >1.2.5
Requires-Dist: tabulate
